nonebot_plugin_chatpdf/__init__.py
nonebot_plugin_chatpdf/config.py
nonebot_plugin_chatpdf/core.py
nonebot_plugin_chatpdf-1.0.0.dist-info/WHEEL
nonebot_plugin_chatpdf-1.0.0.dist-info/METADATA
nonebot_plugin_chatpdf-1.0.0.dist-info/RECORD
